lint_diffs/__init__.py
lint_diffs/default_config
lint_diffs-0.1.22.dist-info/entry_points.txt
lint_diffs-0.1.22.dist-info/LICENSE
lint_diffs-0.1.22.dist-info/WHEEL
lint_diffs-0.1.22.dist-info/METADATA
lint_diffs-0.1.22.dist-info/RECORD
