Metadata-Version: 2.1
Name: lint_diffs
Version: 0.1.22
Summary: Runs one or more linters, but only outputs errors if diffs have lint issues.
Home-page: https://github.com/atakamallc/lint-diffs
License: UNKNOWN
Author: Atakama, LLC
Author-email: dev-support@atakama.com
Requires-Python: >=3.6
Classifier: Intended Audience :: Developers
Classifier: License :: OSI Approved :: GNU Lesser General Public License v3 or later (LGPLv3+)
Classifier: Programming Language :: Python
Classifier: Topic :: Software Development :: Libraries :: Python Modules
Requires-Dist: unidiff>=0.6.0
